anime_episode_parser/__init__.py
anime_episode_parser/cn.py
anime_episode_parser/py.typed
anime_episode_parser-0.0.13.dist-info/licenses/LICENSE
anime_episode_parser-0.0.13.dist-info/WHEEL
anime_episode_parser-0.0.13.dist-info/METADATA
anime_episode_parser-0.0.13.dist-info/RECORD
