Metadata-Version: 2.4
Name: anime-episode-parser
Version: 0.0.13
Summary: A library to parse episode info from anime title
Keywords: anime
Author-email: Trim21 <trim21.me@gmail.com>, RicterZ <ricterzheng@gmail.com>
Requires-Python: >=3.9,<4
License-Expression: MIT
Classifier: Development Status :: 4 - Beta
Classifier: Intended Audience :: Other Audience
Classifier: Natural Language :: Chinese (Traditional)
Classifier: Programming Language :: Python
Classifier: Programming Language :: Python :: 3.9
Classifier: Programming Language :: Python :: 3.10
Classifier: Programming Language :: Python :: 3.11
Classifier: Programming Language :: Python :: 3.12
Classifier: Programming Language :: Python :: 3.13
Classifier: Programming Language :: Python :: Implementation :: CPython
Classifier: Programming Language :: Python :: Implementation :: PyPy
License-File: LICENSE
Project-URL: homepage, https://github.com/BGmi/anime-episode-parser
Project-URL: repository, https://github.com/BGmi/anime-episode-parser
